pixel_ai/__init__.py
pixel_ai/cli.py
pixel_ai/config.py
pixel_ai/inference.py
pixel_ai/utils.py
pixel_ai-0.1.0.dist-info/licenses/LICENSE
pixel_ai-0.1.0.dist-info/METADATA
pixel_ai-0.1.0.dist-info/WHEEL
pixel_ai-0.1.0.dist-info/entry_points.txt
pixel_ai-0.1.0.dist-info/top_level.txt
pixel_ai-0.1.0.dist-info/RECORD
