Metadata-Version: 2.4
Name: pixel-ai
Version: 0.1.0
Summary: Offline Raspberry Pi-optimized LLM for Emotion Mirror Project
Author: Your Name
License-File: LICENSE
Requires-Dist: torch
Requires-Dist: transformers
Requires-Dist: llama-cpp-python
Requires-Dist: click
Requires-Dist: numpy
Requires-Dist: requests
Dynamic: license-file
